sqlalchemy_clickzetta/__init__.py
sqlalchemy_clickzetta/_connector.py
sqlalchemy_clickzetta/_helpers.py
sqlalchemy_clickzetta/_types.py
sqlalchemy_clickzetta/base.py
sqlalchemy_clickzetta/parse_url.py
sqlalchemy_clickzetta/requirements.py
sqlalchemy_clickzetta/version.py
clickzetta_sqlalchemy-0.8.65.3.dist-info/METADATA
clickzetta_sqlalchemy-0.8.65.3.dist-info/WHEEL
clickzetta_sqlalchemy-0.8.65.3.dist-info/entry_points.txt
clickzetta_sqlalchemy-0.8.65.3.dist-info/top_level.txt
clickzetta_sqlalchemy-0.8.65.3.dist-info/RECORD
