Metadata-Version: 2.1
Name: clickzetta-sqlalchemy
Version: 0.8.65.3
Summary: clickzetta python sqlalchemy
Home-page: https://www.zettadecision.com/
Author: mocun
Author-email: "hanmiao.li" <hanmiao.li@clickzetta.com>
Project-URL: documentation, https://www.yunqi.tech/
Platform: Posix; MacOS X;
Requires-Python: >=3.7
Requires-Dist: proto-plus<2.0.0dev,>=1.22.0
Requires-Dist: packaging<24.0.0dev,>=14.3
Requires-Dist: protobuf!=3.20.0,!=3.20.1,!=4.21.0,!=4.21.1,!=4.21.2,!=4.21.3,!=4.21.4,!=4.21.5,<=5.28.1,>=3.19.5
Requires-Dist: python-dateutil<3.0dev,>=2.7.2
Requires-Dist: requests<3.0.0dev,>=2.21.0
Requires-Dist: SQLAlchemy>=1.4
Requires-Dist: future
Requires-Dist: clickzetta-connector>=0.8.78.4
Provides-Extra: all
Requires-Dist: pandas>=1.0.0; extra == "all"
Requires-Dist: db-dtypes<2.0.0dev,>=0.3.0; extra == "all"
Requires-Dist: ipywidgets==7.7.1; extra == "all"
Requires-Dist: geopandas<1.0dev,>=0.9.0; extra == "all"
Requires-Dist: Shapely<2.0dev,>=1.6.0; extra == "all"
Requires-Dist: ipython!=8.1.0,>=7.0.1; extra == "all"
Requires-Dist: tqdm<5.0.0dev,>=4.7.4; extra == "all"
Provides-Extra: geopandas
Requires-Dist: geopandas<1.0dev,>=0.9.0; extra == "geopandas"
Requires-Dist: Shapely<2.0dev,>=1.6.0; extra == "geopandas"
Provides-Extra: ipython
Requires-Dist: ipython!=8.1.0,>=7.0.1; extra == "ipython"
Provides-Extra: ipywidgets
Requires-Dist: ipywidgets==7.7.1; extra == "ipywidgets"
Provides-Extra: pandas
Requires-Dist: pandas>=1.0.0; extra == "pandas"
Requires-Dist: db-dtypes<2.0.0dev,>=0.3.0; extra == "pandas"
Provides-Extra: tqdm
Requires-Dist: tqdm<5.0.0dev,>=4.7.4; extra == "tqdm"
